Metadata-Version: 2.1
Name: django-rest-captcha
Version: 0.3.0
Summary: Lightweight version of django-simple-captcha for work with django-rest-framework
License: MIT
Author: evgeny.zuev
Author-email: zueves@gmail.com
Requires-Python: >=3.8,<4.0
Classifier: License :: OSI Approved :: MIT License
Classifier: Programming Language :: Python :: 3
Classifier: Programming Language :: Python :: 3.8
Classifier: Programming Language :: Python :: 3.9
Classifier: Programming Language :: Python :: 3.10
Classifier: Programming Language :: Python :: 3.11
Requires-Dist: Pillow
Requires-Dist: django (>=4,<5)
Requires-Dist: djangorestframework (>=3,<4)
